<?xml version="1.0" encoding="UTF-8"?>
<con:resource name="/meters/{meterNumber}/PromoPostCardHistory" path="/meters/{meterNumber}/PromoPostCardHistory" id="9c78dd99-1189-4f6d-865b-4b36f765538c" xmlns:xsi="http://www.w3.org/2001/XMLSchema-instance" xmlns:con="http://eviware.com/soapui/config">
  <con:settings>
    <con:setting id="9c78dd99-1189-4f6d-865b-4b36f765538cfileName">%2Fmeters%2F%7BmeterNumber%7D%2FPromoPostCardHistory</con:setting>
  </con:settings>
  <con:parameters>
    <con:parameter required="true">
      <con:name>meterNumber</con:name>
      <con:style>TEMPLATE</con:style>
      <con:dataType>number</con:dataType>
      <con:description xsi:nil="true"/>
    </con:parameter>
  </con:parameters>
  <con:method name="GetPromoPostCardHistory" id="73a3ccc0-4a1a-4c22-898a-9a1c7873cbc5" method="GET">
    <con:description>Get Promo PostCard History</con:description>
    <con:settings/>
    <con:parameters/>
    <con:representation type="RESPONSE">
      <con:mediaType>application/json</con:mediaType>
      <con:status>200</con:status>
      <con:params/>
      <con:sampleContent>{
  "Items" : [ {
    "Id" : 0,
    "DateScanned" : "2015-07-20T15:49:04-07:00",
    "DateCredited" : "2015-07-20T15:49:04-07:00",
    "Status" : "string",
    "PostageAmount" : 1.5
  } ]
}</con:sampleContent>
    </con:representation>
    <con:representation type="RESPONSE">
      <con:mediaType>application/json</con:mediaType>
      <con:status>400</con:status>
      <con:params/>
      <con:sampleContent>"string"</con:sampleContent>
    </con:representation>
    <con:representation type="RESPONSE">
      <con:mediaType>application/json</con:mediaType>
      <con:status/>
      <con:params/>
    </con:representation>
    <con:request name="Request 1" id="5c19b08d-b841-4546-8ff5-302d683462a6" mediaType="application/json">
      <con:settings/>
      <con:endpoint>http://localhost</con:endpoint>
      <con:credentials>
        <con:selectedAuthProfile>No Authorization</con:selectedAuthProfile>
        <con:authType>No Authorization</con:authType>
      </con:credentials>
      <con:parameters/>
    </con:request>
  </con:method>
</con:resource>
